selenium_firefox/__constants.py
selenium_firefox/__firefox_properties.py
selenium_firefox/__init__.py
selenium_firefox/__utils.py
selenium_firefox/firefox.py
selenium_firefox/firefox_addons/__init__.py
selenium_firefox/firefox_addons/addon_manager.py
selenium_firefox/firefox_addons/decentraleyes_addon_settings.py
selenium_firefox/firefox_addons/foxy_proxy_addon_settings.py
selenium_firefox/firefox_addons/https_everywhere_addon_settings.py
selenium_firefox/firefox_addons/noscript_addon_settings.py
selenium_firefox/firefox_addons/privacy_badger_addon_settings.py
selenium_firefox/firefox_addons/ublock_origin_addon_settings.py
selenium_firefox/firefox_addons/builtin_addon_install_settings/__init__.py
selenium_firefox/firefox_addons/builtin_addon_install_settings/builtin_addon_install_settings.py
selenium_firefox/firefox_addons/builtin_addon_install_settings/resources/decentraleyes.xpi
selenium_firefox/firefox_addons/builtin_addon_install_settings/resources/foxy_proxy.xpi
selenium_firefox/firefox_addons/builtin_addon_install_settings/resources/https_everywhere.xpi
selenium_firefox/firefox_addons/builtin_addon_install_settings/resources/noscript.xpi
selenium_firefox/firefox_addons/builtin_addon_install_settings/resources/privacy_badger.xpi
selenium_firefox/firefox_addons/builtin_addon_install_settings/resources/ublock_origin.xpi
selenium_firefox/models/__init__.py
selenium_firefox/models/firefox_capabilities.py
selenium_firefox/models/prefs.py
selenium_firefox-2.0.8.dist-info/LICENSE
selenium_firefox-2.0.8.dist-info/METADATA
selenium_firefox-2.0.8.dist-info/WHEEL
selenium_firefox-2.0.8.dist-info/top_level.txt
selenium_firefox-2.0.8.dist-info/RECORD
