Metadata-Version: 2.1
Name: selenium-firefox
Version: 2.0.8
Summary: selenium_firefox
Home-page: https://github.com/kkristof200/selenium_firefox
Author: Kovács Kristóf-Attila
Classifier: Programming Language :: Python :: 3
Classifier: License :: OSI Approved :: MIT License
Classifier: Operating System :: OS Independent
Requires-Python: >=3.6
License-File: LICENSE
